tsnotes/__init__.py
tsnotes/_modidx.py
tsnotes/core.py
tsnotes-0.0.1.dist-info/LICENSE
tsnotes-0.0.1.dist-info/METADATA
tsnotes-0.0.1.dist-info/WHEEL
tsnotes-0.0.1.dist-info/entry_points.txt
tsnotes-0.0.1.dist-info/top_level.txt
tsnotes-0.0.1.dist-info/RECORD
